facebook_scraper/__init__.py
facebook_scraper/__main__.py
facebook_scraper/constants.py
facebook_scraper/exceptions.py
facebook_scraper/extractors.py
facebook_scraper/facebook_scraper.py
facebook_scraper/fb_types.py
facebook_scraper/page_iterators.py
facebook_scraper/utils.py
facebook_scraper-0.2.58.dist-info/entry_points.txt
facebook_scraper-0.2.58.dist-info/LICENSE
facebook_scraper-0.2.58.dist-info/WHEEL
facebook_scraper-0.2.58.dist-info/METADATA
facebook_scraper-0.2.58.dist-info/RECORD
