Metadata-Version: 2.1
Name: facebook-scraper
Version: 0.2.58
Summary: Scrape Facebook public pages without an API key
Home-page: https://github.com/kevinzg/facebook-scraper
License: MIT
Author: Kevin Zúñiga
Author-email: kevin.zun@gmail.com
Requires-Python: >=3.6,<4.0
Classifier: License :: OSI Approved :: MIT License
Classifier: Programming Language :: Python :: 3
Classifier: Programming Language :: Python :: 3.6
Classifier: Programming Language :: Python :: 3.7
Classifier: Programming Language :: Python :: 3.8
Classifier: Programming Language :: Python :: 3.9
Provides-Extra: browser-cookie3
Provides-Extra: youtube-dl
Requires-Dist: browser-cookie3; extra == "browser-cookie3"
Requires-Dist: dateparser (>=1.0.0,<2.0.0)
Requires-Dist: demjson3 (>=3.0.5,<4.0.0)
Requires-Dist: requests-html (>=0.10.0,<0.11.0)
Requires-Dist: youtube_dl; extra == "youtube-dl"
Project-URL: Repository, https://github.com/kevinzg/facebook-scraper
